{
  "_version": "1.0 — default (all segments, no removals)",
  "topics": [
    {
      "label": "trang_forhud_og_testikler",
      "keywords": ["trang forhud", "dra forhuden", "under forhuden", "penis hodet", "venstre testikkel", "høyre testikkel", "ene testikkelen", "forhuden tilbake"]
    },
    {
      "label": "menn_ereksjon_og_funksjon",
      "keywords": ["får ereksjon", "hard nok", "slapp tilstand", "erigert tilstand", "komme under", "under samleie", "under sex"]
    },
    {
      "label": "kvinners_mens_og_utflod",
      "keywords": ["hatt mensen", "fikk mensen", "fått mensen", "mye utflod", "brun utflod", "uregelmessig mensen", "fått utflod"]
    },
    {
      "label": "prevensjon_p_piller",
      "keywords": ["pillefri uke", "pillefrie uken", "nytt brett", "neste brett", "hvite pillene", "fortsatt beskyttet", "p piller"]
    },
    {
      "label": "graviditetsfrykt_etter_ubeskyttet_sex",
      "keywords": ["ubeskyttet sex", "ubeskyttet samleie", "tok angrepille", "graviditets test", "dager forsinket", "gravid igjen", "beholde barnet"]
    },
    {
      "label": "sti_og_underlivsinfeksjon",
      "keywords": ["påvist klamydia", "fått klamydia", "hatt klamydia", "klamydia kur", "fått herpes", "bakteriell vaginose", "får utbrudd"]
    },
    {
      "label": "sex_forste_gang_og_smerter",
      "keywords": ["første gang", "gjør vondt", "får orgasme", "våt nok", "kåt nok", "stimulere klitoris", "bruke fingrene"]
    },
    {
      "label": "rus_hasj_og_alkohol",
      "keywords": ["røyket hasj", "røyka hasj", "røyker hasj", "drikke alkohol", "kjøpe alkohol", "urin prøve", "tatt kokain"]
    },
    {
      "label": "snus_og_nikotin",
      "keywords": ["prøvde snus", "prøvd snus", "nikotinfri snus", "tannlegen ser", "prikk snus", "slutte å snuse"]
    },
    {
      "label": "psykisk_helse_angst_og_tvang",
      "keywords": ["sosial angst", "tvangs tanker", "dårlige tanker", "psykisk lidelse", "psykiske problemer", "sosiale settinger", "sosiale situasjoner"]
    },
    {
      "label": "selvskading_og_selvmordstanker",
      "keywords": ["selvmords tanker", "drepe meg selv", "gjør selvskading", "trenger hjelp", "trist hele", "leve lenger", "leve mer"]
    },
    {
      "label": "vgs_opptak_og_studiekompetanse",
      "keywords": ["generell studiekompetanse", "samordna opptak", "ordinær kvote", "søke vgs", "søke videregående", "høyere utdanning", "videregående skole"]
    },
    {
      "label": "eksamen_og_privatist",
      "keywords": ["privatist eksamen", "muntlig eksamen", "skriftlig eksamen", "første året", "siste året", "høyt snitt", "engelsk fordypning"]
    },
    {
      "label": "skolehverdag_anmerkning_og_larer",
      "keywords": ["fikk anmerkning", "får anmerkning", "sette anmerkning", "lærer lov", "læreren tvinge", "foran klassen", "bytte klasse"]
    },
    {
      "label": "forerkort_og_vegvesen",
      "keywords": ["trafikalt grunnkurs", "førerkort klasse", "bil lappen", "mistet lappen", "mistet førerkortet", "statens vegvesen", "lett motorsykkel"]
    },
    {
      "label": "jobb_lonn_og_stilling",
      "keywords": ["søke jobb", "høyere lønn", "fast stilling", "fast ansatt", "får betalt", "får lønn", "jobber timer"]
    },
    {
      "label": "hverdagsjus_politi_og_forelegg",
      "keywords": ["forenklet forelegg", "politiet lov", "norsk lov", "norsk statsborgerskap", "norsk pass", "pengene tilbake", "privat eiendom"]
    },
    {
      "label": "familie_konflikt_foreldre",
      "keywords": ["skilte foreldre", "mamma krangler", "pappa krangler", "foreldre kontroll", "pappa bor", "kommer hjem", "får lov"]
    },
    {
      "label": "forelskelse_folelser_for_en_person",
      "keywords": ["skikkelig forelsket", "sykt forelsket", "jente liker", "liker ham", "fått følelser", "kontakt igjen", "møtes igjen"]
    },
    {
      "label": "forhold_brudd_og_ambivalens",
      "keywords": ["mistet følelser", "hele forholdet", "forholdet vårt", "forholdet våres", "tidligere forhold", "sammen igjen", "fint samme"]
    },
    {
      "label": "spiseforstyrrelse_og_kroppsvekt",
      "keywords": ["spise mindre", "spise mer", "aldri sulten", "rundt kalorier", "dårlig samvittighet", "spiser mye", "sliter vekt"]
    }
  ]
}
